acdh_id_reconciler/__init__.py
acdh_id_reconciler/utils.py
acdh_id_reconciler-0.7.1.dist-info/LICENSE
acdh_id_reconciler-0.7.1.dist-info/METADATA
acdh_id_reconciler-0.7.1.dist-info/WHEEL
acdh_id_reconciler-0.7.1.dist-info/top_level.txt
acdh_id_reconciler-0.7.1.dist-info/RECORD
