Metadata-Version: 2.1
Name: acdh-id-reconciler
Version: 0.7.1
Summary: Python package to reconcile GND, GeoNames IDs via WikiData
Home-page: https://github.com/acdh-oeaw/acdh-id-reconciler
Author: Peter Andorfer
Author-email: peter.andorfer@oeaw.ac.at
License: MIT license
Classifier: Intended Audience :: Developers
Classifier: License :: OSI Approved :: MIT License
Classifier: Natural Language :: English
Requires-Python: >=3.8
License-File: LICENSE
Requires-Dist: acdh-arche-assets <4,>=3.6
Requires-Dist: requests <3,>2.2
Requires-Dist: SPARQLWrapper <3,>=1.8.5
